rsyncx/__init__.py
rsyncx/config.dist.py
rsyncx/main.py
rsyncx/rsync_command.py
rsyncx-0.1.3.dist-info/licenses/LICENSE
rsyncx-0.1.3.dist-info/METADATA
rsyncx-0.1.3.dist-info/WHEEL
rsyncx-0.1.3.dist-info/entry_points.txt
rsyncx-0.1.3.dist-info/top_level.txt
rsyncx-0.1.3.dist-info/RECORD
