Metadata-Version: 2.4
Name: rsyncx
Version: 0.1.3
Summary: Sincroniza tus datos de manera segura con rsyncx (basado en rsync) donde se incluye papelera para no perder datos, con .ignore para ignorar archivos o carpetas y válidao para Synology o Servidor.
Author: Mario x
License: MIT
Project-URL: Homepage, https://github.com/pistatxos/rsyncx
Project-URL: Repository, https://github.com/pistatxos/rsyncx
Project-URL: Issues, https://github.com/pistatxos/rsyncx/issues
Keywords: rsync,sync,backup,Synology,NAS,mirror,CLI
Classifier: Programming Language :: Python :: 3
Classifier: License :: OSI Approved :: MIT License
Classifier: Operating System :: POSIX :: Linux
Requires-Python: >=3.8
License-File: LICENSE
Dynamic: license-file
Dynamic: requires-python
